docker_registry_purger/__init__.py
docker_registry_purger-0.1.1.dist-info/METADATA
docker_registry_purger-0.1.1.dist-info/RECORD
docker_registry_purger-0.1.1.dist-info/WHEEL
docker_registry_purger-0.1.1.dist-info/entry_points.txt
docker_registry_purger-0.1.1.dist-info/top_level.txt
docker_registry_purger-0.1.1.dist-info/zip-safe
