Metadata-Version: 2.1
Name: docker-registry-purger
Version: 0.1.1
Summary: A simple docker registry cleaner
Home-page: http://github.com/polyconseil/docker-registry-purger
Author: Polyconseil
Author-email: opensource+docker-registry-purger@polyconseil.fr
License: BSD 3-Clause License
Keywords: docker,docker-registry,cleaner
Platform: UNKNOWN
Classifier: Development Status :: 4 - Beta
Classifier: Environment :: Console
Classifier: Intended Audience :: Developers
Classifier: Intended Audience :: Information Technology
Classifier: Intended Audience :: System Administrators
Classifier: License :: OSI Approved :: BSD License
Classifier: Natural Language :: English
Classifier: Operating System :: OS Independent
Classifier: Programming Language :: Python :: 3
Classifier: Programming Language :: Python :: 3.4
Classifier: Programming Language :: Python :: 3.5
Classifier: Programming Language :: Python :: 3.6
Classifier: Programming Language :: Python :: 3.7
Classifier: Programming Language :: Python :: 3 :: Only
Classifier: Topic :: System :: Software Distribution
Classifier: Topic :: System :: Systems Administration
Classifier: Topic :: Utilities
Requires-Dist: click
Requires-Dist: daiquiri
Requires-Dist: isodate
Requires-Dist: requests
